langevals/__init__.py
langevals/evaluation.py
langevals/expect.py
langevals/pytest_plugins/__init__.py
langevals/pytest_plugins/pass_rate_plugin.py
langevals/server.py
langevals/utils.py
langevals-0.1.7.dist-info/LICENSE.md
langevals-0.1.7.dist-info/METADATA
langevals-0.1.7.dist-info/WHEEL
langevals-0.1.7.dist-info/entry_points.txt
langevals-0.1.7.dist-info/RECORD
